{"cameraMode":{"drawMode":0,"name":"Shaded","section":"Shading Mode"},"sceneLighting":false,"audioPlay":false,"sceneViewState":{"showFog":true,"showMaterialUpdate":false,"showSkybox":false,"showFlares":true,"showImageEffects":true,"showParticleSystems":true},"in2DMode":false,"pivot":{"x":-5.3725481033325199,"y":3.1810050010681154,"z":3.85809588432312},"rotation":{"x":-0.14698447287082673,"y":-0.8045612573623657,"z":0.22293764352798463,"w":-0.5304560661315918},"size":0.7788084149360657,"orthographic":false}